Webstore_ScrapperPY/__init__.py
Webstore_ScrapperPY/scrape.py
Webstore_ScrapperPY-0.1.dist-info/METADATA
Webstore_ScrapperPY-0.1.dist-info/WHEEL
Webstore_ScrapperPY-0.1.dist-info/top_level.txt
Webstore_ScrapperPY-0.1.dist-info/RECORD
