Metadata-Version: 2.1
Name: Webstore-ScrapperPY
Version: 0.1
Summary: A simple wrapper to scrape data from a web store.
Home-page: https://github.com/Scottyboi1/Webstore_ScrapperPY
Author: Scott Avery
Author-email: scottavery2001@gmail.com
Classifier: Programming Language :: Python :: 3
Classifier: License :: OSI Approved :: MIT License
Classifier: Operating System :: OS Independent
Requires-Python: >=3.6
Requires-Dist: requests
